duckdb_flyway/__init__.py
duckdb_flyway/duckdb_flyway.py
duckdb_flyway/duckdb_flyway_test.py
duckdb_flyway-0.1.1.dist-info/METADATA
duckdb_flyway-0.1.1.dist-info/WHEEL
duckdb_flyway-0.1.1.dist-info/licenses/LICENSE
duckdb_flyway-0.1.1.dist-info/RECORD
