Metadata-Version: 2.4
Name: duckdb-flyway
Version: 0.1.1
Summary: DuckDB migrations tool
Project-URL: Homepage, https://github.com/aluxian/duckdb-flyway
Project-URL: Repository, https://github.com/aluxian/duckdb-flyway.git
Project-URL: Issues, https://github.com/aluxian/duckdb-flyway/issues
Project-URL: Changelog, https://github.com/aluxian/duckdb-flyway/releases
Author-email: Alexandru Rosianu <me@aluxian.com>
License-Expression: MIT
License-File: LICENSE
Keywords: database,duckdb,flyway,migrations
Classifier: Development Status :: 4 - Beta
Classifier: Intended Audience :: Developers
Classifier: License :: OSI Approved :: MIT License
Classifier: Operating System :: OS Independent
Classifier: Programming Language :: Python :: 3
Classifier: Programming Language :: Python :: 3.12
Classifier: Topic :: Database
Classifier: Topic :: Software Development :: Libraries :: Python Modules
Classifier: Typing :: Typed
Requires-Python: >=3.12
Requires-Dist: duckdb>=1.1.3
Requires-Dist: loguru>=0.7.3
